cccodes/__init__.py
cccodes/badwords.py
cccodes/coupon.py
cccodes/couponcode_test.py
cccodes-0.1.2.dist-info/LICENSE
cccodes-0.1.2.dist-info/METADATA
cccodes-0.1.2.dist-info/WHEEL
cccodes-0.1.2.dist-info/RECORD
